satispaython/__init__.py
satispaython/api.py
satispaython/auth.py
satispaython/client.py
satispaython/utils/__init__.py
satispaython/utils/utils.py
satispaython-0.4.0.dist-info/LICENSE
satispaython-0.4.0.dist-info/WHEEL
satispaython-0.4.0.dist-info/METADATA
satispaython-0.4.0.dist-info/RECORD
