Metadata-Version: 2.1
Name: satispaython
Version: 0.4.0
Summary: A simple library to manage Satispay payments following the Web-button flow.
Home-page: https://github.com/otto-torino/satispaython
License: MIT
Keywords: python,satispay
Author: Daniele Pira
Author-email: daniele.pira@otto.to.it
Requires-Python: >=3.6,<4.0
Classifier: License :: OSI Approved :: MIT License
Classifier: Programming Language :: Python :: 3
Classifier: Programming Language :: Python :: 3.6
Classifier: Programming Language :: Python :: 3.7
Classifier: Programming Language :: Python :: 3.8
Classifier: Programming Language :: Python :: 3.9
Classifier: Topic :: Software Development :: Libraries :: Python Modules
Requires-Dist: cryptography (>=3.4,<4.0)
Requires-Dist: httpx (>=0.16,<0.17)
Project-URL: Repository, https://github.com/otto-torino/satispaython
